highspy/__init__.py
highspy/__init__.pyi
highspy/_core/__init__.pyi
highspy/_core/cb.pyi
highspy/_core/simplex_constants.pyi
highspy/_core.cp39-win32.pyd
highspy/highs.py
highspy-1.8.0.dist-info/METADATA
highspy-1.8.0.dist-info/WHEEL
highspy-1.8.0.dist-info/licenses/AUTHORS
highspy-1.8.0.dist-info/licenses/LICENSE.txt
highspy-1.8.0.dist-info/RECORD
