Metadata-Version: 2.1
Name: highspy
Version: 1.8.0
Summary: A thin set of pybind11 wrappers to HiGHS
Author-Email: HiGHS developers <highsopt@gmail.com>
Classifier: License :: OSI Approved :: MIT License
Classifier: Programming Language :: Python :: 3 :: Only
Classifier: Programming Language :: Python :: 3.8
Classifier: Programming Language :: Python :: 3.9
Classifier: Programming Language :: Python :: 3.10
Classifier: Programming Language :: Python :: 3.11
Classifier: Programming Language :: Python :: 3.12
Classifier: Typing :: Typed
Project-URL: Source code, https://github.com/ERGO-Code/HiGHS
Project-URL: Bug tracker, https://github.com/ERGO-Code/HiGHS/issues
Requires-Python: >=3.8
Requires-Dist: numpy
Requires-Dist: pytest; extra == "test"
Requires-Dist: numpy; extra == "test"
Provides-Extra: test
